harness_ccm_external_data/__init__.py
harness_ccm_external_data/focus_data.py
harness_ccm_external_data-0.1.5.dist-info/LICENSE
harness_ccm_external_data-0.1.5.dist-info/METADATA
harness_ccm_external_data-0.1.5.dist-info/WHEEL
harness_ccm_external_data-0.1.5.dist-info/RECORD
