Metadata-Version: 2.3
Name: harness-ccm-external-data
Version: 0.1.5
Summary: Tools to help manage external data for Harness CCM
Author: Riley Snyder
Author-email: riley.snyder@harness.io
Requires-Python: >=3.13
Classifier: Programming Language :: Python :: 3
Classifier: Programming Language :: Python :: 3.13
Requires-Dist: pandas (>=2.3.0,<3.0.0)
Requires-Dist: requests (>=2.32.4,<3.0.0)
